api/__init__.py
api/deco.py
api/exceptions.py
api/interfaces.py
api/logger.py
api/parsing.py
conf/__init__.py
conf/gatherfailed.py
conf/languages.py
conf/settings.py
htmldata/__init__.py
htmldata/htmlfilewriter.py
htmldata/jsonwriter.py
htmldata/template.py
htmldata/common/__init__.py
htmldata/lib/__init__.py
htmldata/libdoc/__init__.py
htmldata/rebot/__init__.py
htmldata/testdoc/__init__.py
libdocpkg/__init__.py
libdocpkg/builder.py
libdocpkg/consoleviewer.py
libdocpkg/datatypes.py
libdocpkg/htmlutils.py
libdocpkg/htmlwriter.py
libdocpkg/jsonbuilder.py
libdocpkg/jsonwriter.py
libdocpkg/model.py
libdocpkg/output.py
libdocpkg/robotbuilder.py
libdocpkg/standardtypes.py
libdocpkg/writer.py
libdocpkg/xmlbuilder.py
libdocpkg/xmlwriter.py
libraries/BuiltIn.py
libraries/Collections.py
libraries/DateTime.py
libraries/Dialogs.py
libraries/Easter.py
libraries/OperatingSystem.py
libraries/Process.py
libraries/Remote.py
libraries/Reserved.py
libraries/Screenshot.py
libraries/String.py
libraries/Telnet.py
libraries/XML.py
libraries/__init__.py
libraries/dialogs_py.py
model/__init__.py
model/body.py
model/configurer.py
model/control.py
model/filter.py
model/fixture.py
model/itemlist.py
model/keyword.py
model/message.py
model/metadata.py
model/modelobject.py
model/modifier.py
model/namepatterns.py
model/statistics.py
model/stats.py
model/suitestatistics.py
model/tags.py
model/tagsetter.py
model/tagstatistics.py
model/testcase.py
model/testsuite.py
model/totalstatistics.py
model/visitor.py
output/__init__.py
output/debugfile.py
output/filelogger.py
output/librarylogger.py
output/listenerarguments.py
output/listenermethods.py
output/listeners.py
output/logger.py
output/loggerhelper.py
output/output.py
output/pyloggingconf.py
output/stdoutlogsplitter.py
output/xmllogger.py
output/console/__init__.py
output/console/dotted.py
output/console/highlighting.py
output/console/quiet.py
output/console/verbose.py
parsing/__init__.py
parsing/suitestructure.py
parsing/lexer/__init__.py
custom_robot-1.0.1.dist-info/METADATA
custom_robot-1.0.1.dist-info/WHEEL
custom_robot-1.0.1.dist-info/top_level.txt
custom_robot-1.0.1.dist-info/RECORD
