Metadata-Version: 2.1
Name: custom-robot
Version: 1.0.1
Summary: Customized version of the robot package
Author: Rishi Varma
Author-email: rishi@criterionnetworks.com
License: GPL
Classifier: Programming Language :: Python :: 3
Classifier: Programming Language :: Python :: 3.6
Classifier: Programming Language :: Python :: 3.7
Classifier: Programming Language :: Python :: 3.8
Classifier: Programming Language :: Python :: 3.9
Classifier: Programming Language :: Python :: 3.10
Classifier: License :: OSI Approved :: GNU General Public License (GPL)
Classifier: Operating System :: OS Independent
Requires-Python: >=3.6
